[
  {
    "token": "0a2b9d2e-ac35-4097-b87b-95472cfe4767",
    "filePath": "/files/jyy-guitars.wav",
    "createdAt": "2025-06-03T17:38:19.998Z",
    "expiresInMinutes": 60,
    "orderId": "d05fd80d-3107-4627-8298-32dfe49b29e7",
    "downloadStarted": false,
    "downloadCompleted": false
  },
  {
    "token": "e8bd2bd0-0c87-4c5e-93fd-c51445f553e5",
    "filePath": "/files/anomic-drums.wav",
    "createdAt": "2025-06-03T17:38:20.125Z",
    "expiresInMinutes": 60,
    "orderId": "d05fd80d-3107-4627-8298-32dfe49b29e7",
    "downloadStarted": false,
    "downloadCompleted": false
  },
  {
    "token": "d8290997-a65c-4ab2-853e-697e86928afd",
    "filePath": "/files/dark-keys.wav",
    "createdAt": "2025-06-03T17:38:20.277Z",
    "expiresInMinutes": 60,
    "orderId": "d05fd80d-3107-4627-8298-32dfe49b29e7",
    "downloadStarted": false,
    "downloadCompleted": false
  },
  {
    "token": "334c042a-498e-4065-bd33-79f71bffb8ff",
    "filePath": "/files/reddown-bass.wav",
    "createdAt": "2025-06-03T17:38:20.419Z",
    "expiresInMinutes": 60,
    "orderId": "d05fd80d-3107-4627-8298-32dfe49b29e7",
    "downloadStarted": false,
    "downloadCompleted": false
  },
  {
    "token": "6deed637-a039-4735-9dd1-44d80c301f4e",
    "filePath": "/files/atlantic-guitar.wav",
    "createdAt": "2025-06-03T17:38:20.578Z",
    "expiresInMinutes": 60,
    "orderId": "d05fd80d-3107-4627-8298-32dfe49b29e7",
    "downloadStarted": false,
    "downloadCompleted": false
  },
  {
    "token": "647964d8-7390-4aca-981c-4aa5ec4c3ce2",
    "filePath": "/files/out-dark-drums.wav",
    "createdAt": "2025-06-03T17:38:20.663Z",
    "expiresInMinutes": 60,
    "orderId": "d05fd80d-3107-4627-8298-32dfe49b29e7",
    "downloadStarted": true,
    "downloadCompleted": true,
    "deviceFingerprint": "eyJ1c2VyQWdlbnQi",
    "userAgent": "Mozilla/5.0 (Macintosh; Intel Mac OS X 10_15_7) AppleWebKit/537.36 (KHTML, like Gecko) Chrome/136.0.0.0 Safari/537.36",
    "startedAt": "2025-06-03T17:38:47.049Z",
    "completedAt": "2025-06-03T17:38:50.073Z"
  },
  {
    "token": "5358a8e7-5df1-4a38-a032-646a5375848b",
    "filePath": "/files/quietness-bass.wav",
    "createdAt": "2025-06-03T17:38:20.775Z",
    "expiresInMinutes": 60,
    "orderId": "d05fd80d-3107-4627-8298-32dfe49b29e7",
    "downloadStarted": false,
    "downloadCompleted": false
  },
  {
    "token": "3c045103-a9d3-41ed-bd69-e016b167fa2e",
    "filePath": "/files/feign-guitars.wav",
    "createdAt": "2025-06-03T17:38:20.871Z",
    "expiresInMinutes": 60,
    "orderId": "d05fd80d-3107-4627-8298-32dfe49b29e7",
    "downloadStarted": false,
    "downloadCompleted": false
  }
]